{
  "defaultTheme": "sea",
  "themes": {
    "sea": {
      "label": "Sea Green",
      "tokens": {
        "background": "#f6fbfb",
        "foreground": "#142624",
        "color-blue-50": "#eafaf9",
        "color-blue-100": "#d3f3f1",
        "color-blue-200": "#b8ebe8",
        "color-blue-300": "#8edfd9",
        "color-blue-400": "#5ecfc8",
        "color-blue-500": "#38bdb6",
        "color-blue-600": "#20b2aa",
        "color-blue-700": "#1b9690",
        "color-blue-800": "#167975",
        "color-blue-900": "#125d59",
        "color-cyan-50": "#eafaf9",
        "color-cyan-100": "#d3f3f1",
        "color-cyan-200": "#b8ebe8",
        "color-cyan-300": "#8edfd9",
        "color-cyan-400": "#5ecfc8",
        "color-cyan-500": "#38bdb6",
        "color-cyan-600": "#20b2aa",
        "color-cyan-700": "#1b9690",
        "color-cyan-800": "#167975",
        "color-cyan-900": "#125d59",
        "color-neutral-50": "#f6fbfb",
        "color-neutral-100": "#eef6f6",
        "color-neutral-200": "#dbe7e7",
        "color-neutral-300": "#c7d6d5",
        "color-neutral-400": "#95abaa",
        "color-neutral-500": "#6c8381",
        "color-neutral-600": "#4e6563",
        "color-neutral-700": "#374b49",
        "color-neutral-800": "#243634",
        "color-neutral-900": "#142624",
        "color-red-50": "#fef2f2",
        "color-red-100": "#fee2e2",
        "color-red-200": "#fecaca",
        "color-red-300": "#fca5a5",
        "color-red-400": "#f87171",
        "color-red-500": "#ef4444",
        "color-red-600": "#dc2626",
        "color-red-700": "#b91c1c"
      }
    },
    "sea-dark": {
      "label": "Sea Deep",
      "tokens": {
        "background": "#f3f9f9",
        "foreground": "#10211f",
        "color-blue-50": "#e3f7f6",
        "color-blue-100": "#cdeeed",
        "color-blue-200": "#9fdad7",
        "color-blue-300": "#76cac7",
        "color-blue-400": "#4ab9b4",
        "color-blue-500": "#2aa8a2",
        "color-blue-600": "#198f8a",
        "color-blue-700": "#147673",
        "color-blue-800": "#105f5c",
        "color-blue-900": "#0d4a48",
        "color-cyan-50": "#e3f7f6",
        "color-cyan-100": "#cdeeed",
        "color-cyan-200": "#9fdad7",
        "color-cyan-300": "#76cac7",
        "color-cyan-400": "#4ab9b4",
        "color-cyan-500": "#2aa8a2",
        "color-cyan-600": "#198f8a",
        "color-cyan-700": "#147673",
        "color-cyan-800": "#105f5c",
        "color-cyan-900": "#0d4a48",
        "color-neutral-50": "#f3f9f9",
        "color-neutral-100": "#e9f2f2",
        "color-neutral-200": "#d3e1e0",
        "color-neutral-300": "#bdcecd",
        "color-neutral-400": "#8da3a1",
        "color-neutral-500": "#647a78",
        "color-neutral-600": "#4a5f5d",
        "color-neutral-700": "#344744",
        "color-neutral-800": "#233230",
        "color-neutral-900": "#10211f",
        "color-red-50": "#fef2f2",
        "color-red-100": "#fee2e2",
        "color-red-200": "#fecaca",
        "color-red-300": "#fca5a5",
        "color-red-400": "#f87171",
        "color-red-500": "#ef4444",
        "color-red-600": "#dc2626",
        "color-red-700": "#b91c1c"
      }
    }
  }
}
